alumath_peergroup19/__init__.py
alumath_peergroup19/matrix_operations.py
alumath_peergroup19-1.0.6.dist-info/METADATA
alumath_peergroup19-1.0.6.dist-info/WHEEL
alumath_peergroup19-1.0.6.dist-info/top_level.txt
alumath_peergroup19-1.0.6.dist-info/RECORD
